LICENSE
README.md
setup.py
qmetry_pytest/__init__.py
qmetry_pytest/config.py
qmetry_pytest/plugin.py