Metadata-Version: 2.1
Name: qmetry-pytest
Version: 1.0.2
Summary: A PyTest plugin that provides seamless integration with QMetry Test Management Platform.
Home-page: https://github.com/prashanth-sams/qmetry-pytest
Author: Prashanth Sams
Author-email: sams.prashanth@gmail.com
Maintainer: Prashanth Sams
Maintainer-email: sams.prashanth@gmail.com
License: MIT
Keywords: qmetry,qmetry pytest,reporter,report,pytest,py.test,jira,cucumber,xml
Platform: UNKNOWN
Classifier: Framework :: Pytest
Classifier: Topic :: Software Development :: Testing
Classifier: Programming Language :: Python
Classifier: Operating System :: OS Independent
Classifier: License :: OSI Approved :: MIT License
Requires-Python: >=3.5
License-File: LICENSE
